[
  {
    "name": "hrs-team-leader",
    "label": "HRS Team Leader",
    "description": "Team Leader has access to all hearings for all services",
    "category": "ADMIN",
    "substantive": false,
    "type": "ORGANISATION",
    "patterns": [
      {
        "roleType": {
          "mandatory": true,
          "values": ["ORGANISATION"]
        },
        "grantType": {
          "mandatory": true,
          "values": ["STANDARD"]
        },
        "classification": {
          "mandatory": true,
          "values": ["PUBLIC"]
        },
        "attributes": {
          "jurisdiction": {
            "mandatory": true,
            "values": ["HRS"]
          },
          "primaryLocation": {
            "mandatory": true
          }
        }
      }
    ]
  },
  {
    "name": "hrs-listener",
    "label": "HRS Listener",
    "description": "allows a user to listen to a hearing recording for the skills selected",
    "category": "ADMIN",
    "substantive": false,
    "type": "ORGANISATION",
    "patterns": [
      {
        "roleType": {
          "mandatory": true,
          "values": ["ORGANISATION"]
        },
        "grantType": {
          "mandatory": true,
          "values": ["STANDARD"]
        },
        "classification": {
          "mandatory": true,
          "values": ["PUBLIC"]
        },
        "attributes": {
          "jurisdiction": {
            "mandatory": true,
            "values": ["HRS"]
          },
          "primaryLocation": {
            "mandatory": true
          }
        }
      }
    ]
  },
  {
    "name": "hrs-sharer",
    "label": "HRS Sharer",
    "description": "allows a user to share a hearing recording for the skills selected",
    "category": "ADMIN",
    "substantive": false,
    "type": "ORGANISATION",
    "patterns": [
      {
        "roleType": {
          "mandatory": true,
          "values": ["ORGANISATION"]
        },
        "grantType": {
          "mandatory": true,
          "values": ["STANDARD"]
        },
        "classification": {
          "mandatory": true,
          "values": ["PUBLIC"]
        },
        "attributes": {
          "jurisdiction": {
            "mandatory": true,
            "values": ["HRS"]
          },
          "primaryLocation": {
            "mandatory": true
          }
        }
      }
    ]
  }
]
