<databaseChangeLog xmlns="http://www.liquibase.org/xml/ns/dbchangelog"
                   xmlns:xsi="http://www.w3.org/2001/XMLSchema-instance"
                   xsi:schemaLocation="http://www.liquibase.org/xml/ns/dbchangelog http://www.liquibase.org/xml/ns/dbchangelog/dbchangelog-3.1.xsd">

  <changeSet id="10" author="nitin.sahu@hmcts.net">
    <createTable tableName="actor_cache_control">
      <column name="actor_id" type="uuid">
        <constraints nullable="false" primaryKey="true"/>
      </column>
      <column name="etag" type="integer">
        <constraints nullable="false"/>
      </column>
      <column name="json_response" type="jsonb">
        <constraints nullable="false"/>
      </column>
    </createTable>
  </changeSet>
</databaseChangeLog>
